README.md
setup.py
background_removal.egg-info/PKG-INFO
background_removal.egg-info/SOURCES.txt
background_removal.egg-info/dependency_links.txt
background_removal.egg-info/requires.txt
background_removal.egg-info/top_level.txt
bgr_removal/__init__.py
bgr_removal/inference.py
bgr_removal/inference_utils.py
bgr_removal/model/__init__.py
bgr_removal/model/decoder.py
bgr_removal/model/deep_guided_filter.py
bgr_removal/model/fast_guided_filter.py
bgr_removal/model/lraspp.py
bgr_removal/model/mobilenetv3.py
bgr_removal/model/model.py
bgr_removal/model/resnet.py